LICENSE
MANIFEST.in
README.rst
setup.py
imgurup/__init__.py
imgurup.egg-info/PKG-INFO
imgurup.egg-info/SOURCES.txt
imgurup.egg-info/dependency_links.txt
imgurup.egg-info/entry_points.txt
imgurup.egg-info/top_level.txt
imgurup/data/imgurup.desktop
tests/test_imgurup.py