Metadata-Version: 1.1
Name: imgurup
Version: 1.6.0
Summary: Upload to imgur using API(v3). Support CLI, KDE,Zenity(GTK) and Mac dialog upload. And you can also use your account to upload :).
Home-page: https://github.com/carlcarl/imgurup
Author: carlcarl
Author-email: carlcarlking@gmail.com
License: MIT
Platform: UNKNOWN
Classifier: Development Status :: 5 - Production/Stable
Classifier: Intended Audience :: End Users/Desktop
Classifier: License :: OSI Approved :: MIT License
Classifier: Programming Language :: Python
Classifier: Operating System :: MacOS :: MacOS X
Classifier: Operating System :: POSIX
Classifier: Operating System :: Unix
Classifier: Topic :: Utilities
Classifier: Topic :: Software Development :: Libraries
